Metadata-Version: 2.1
Name: otoware
Version: 1.1.1
Summary: otoware
Home-page: https://ku-jinja.net
Author: kkiyama117
Author-email: k.kiyama117@gmail.com
License: UNKNOWN
Keywords: python
Platform: UNKNOWN
Classifier: Programming Language :: Python
Provides-Extra: testing
